algorand_governance_oracle/api.py
algorand_governance_oracle/application.py
algorand_governance_oracle/clients.py
algorand_governance_oracle/deployment.py
algorand_governance_oracle-0.2.0.dist-info/LICENSE
algorand_governance_oracle-0.2.0.dist-info/METADATA
algorand_governance_oracle-0.2.0.dist-info/WHEEL
algorand_governance_oracle-0.2.0.dist-info/top_level.txt
algorand_governance_oracle-0.2.0.dist-info/RECORD
