Metadata-Version: 2.1
Name: algorand-governance-oracle
Version: 0.2.0
Summary: Statistics related with the current governance period.
Home-page: https://github.com/Hipo/algorand-governance-oracle
Author: hipo
Author-email: pypi@hipolabs.com
License: MIT
Platform: UNKNOWN
Classifier: Intended Audience :: Developers
Classifier: Operating System :: OS Independent
Classifier: Programming Language :: Python
Classifier: Programming Language :: Python :: 3
Classifier: Programming Language :: Python :: 3.7
Classifier: Programming Language :: Python :: 3.8
Classifier: Programming Language :: Python :: 3.9
Classifier: Programming Language :: Python :: 3.10
Classifier: Topic :: Internet :: WWW/HTTP
Classifier: Topic :: Internet :: WWW/HTTP :: Dynamic Content
Requires-Python: >=3.7
License-File: LICENSE
Requires-Dist: pyteal (==0.18.0)
Requires-Dist: py-algorand-sdk (==1.17.0)
